artificery/__init__.py
artificery/artificery.py
artificery/parsers/__init__.py
artificery/parsers/add/parse.py
artificery/parsers/categorical_regression/parse.py
artificery/parsers/combine_in_out_res/parse.py
artificery/parsers/convblock/parse.py
artificery/parsers/custom_layer/parse.py
artificery/parsers/fm_range_apply/parse.py
artificery/parsers/hindsight_warp/parse.py
artificery/parsers/identity/parse.py
artificery/parsers/interpolate/parse.py
artificery/parsers/log_softmax/parse.py
artificery/parsers/mask_output_based_on_input/parse.py
artificery/parsers/masked_normalize/parse.py
artificery/parsers/modelwithweights/parse.py
artificery/parsers/optimizer/parse.py
artificery/parsers/rollback_warp/parse.py
artificery/parsers/scalenet/parse.py
artificery/parsers/sequence/parse.py
artificery/parsers/siamese_net/parse.py
artificery/parsers/split_processor/parse.py
artificery/parsers/transparentseq/parse.py
artificery/parsers/upsample_residuals/parse.py
artificery/parsers/warp_with_input_downmodule/parse.py
artificery-0.0.3.3.dist-info/LICENSE
artificery-0.0.3.3.dist-info/METADATA
artificery-0.0.3.3.dist-info/WHEEL
artificery-0.0.3.3.dist-info/top_level.txt
artificery-0.0.3.3.dist-info/RECORD
