Metadata-Version: 2.1
Name: artificery
Version: 0.0.3.3
Summary: A tool for building pyrorch nets from spec files
Home-page: https://github.com/supersergiy/artificery
Author: Sergiy Popovych
Author-email: sergiy.popovich@gmail.com
License: UNKNOWN
Platform: UNKNOWN
Requires-Dist: scalenet
Requires-Dist: torch
Requires-Dist: torchvision
